beets_mpd_utils-0.3.5.dist-info/licenses/LICENSE
beetsplug/mpd_utils/__init__.py
beetsplug/mpd_utils/mpd_dj.py
beetsplug/mpd_utils/mpd_tracker.py
beetsplug/mpd_utils/utils.py
beets_mpd_utils-0.3.5.dist-info/METADATA
beets_mpd_utils-0.3.5.dist-info/WHEEL
beets_mpd_utils-0.3.5.dist-info/top_level.txt
beets_mpd_utils-0.3.5.dist-info/RECORD
