Metadata-Version: 2.4
Name: beets-mpd-utils
Version: 0.3.5
Summary: Utilities for MPD integration with Beets
Project-URL: homepage, https://github.com/thekakkun/beets-mpd-utils
Project-URL: repository, https://github.com/thekakkun/beets-mpd-utils.git
Requires-Python: >=3.12
License-File: LICENSE
Requires-Dist: beets>=2.3.1
Requires-Dist: python-mpd2>=3.1.1
Dynamic: license-file
